aws_cost_mutilator/__init__.py
aws_cost_mutilator/__main__.py
aws_cost_mutilator/ec2.py
aws_cost_mutilator/iam.py
aws_cost_mutilator/s3.py
aws_cost_mutilator/tests.py
aws_cost_mutilator-0.2.1.dist-info/LICENSE
aws_cost_mutilator-0.2.1.dist-info/METADATA
aws_cost_mutilator-0.2.1.dist-info/WHEEL
aws_cost_mutilator-0.2.1.dist-info/entry_points.txt
aws_cost_mutilator-0.2.1.dist-info/RECORD
